TracNewsFlash-1.0.3.dist-info/DESCRIPTION.rst
TracNewsFlash-1.0.3.dist-info/METADATA
TracNewsFlash-1.0.3.dist-info/RECORD
TracNewsFlash-1.0.3.dist-info/WHEEL
TracNewsFlash-1.0.3.dist-info/entry_points.txt
TracNewsFlash-1.0.3.dist-info/metadata.json
TracNewsFlash-1.0.3.dist-info/top_level.txt
newsflash/__init__.py
newsflash/macro.py
newsflash/htdocs/css/newsflash.css
